money_bags/__init__.py
money_bags/constants/__init__.py
money_bags/constants/country_constants.py
money_bags/constants/currency_constants.py
money_bags/constants/general_constants.py
money_bags/constants/iso_details.py
money_bags/constants/zone_constants.py
money_bags/country_specifics/__init__.py
money_bags/money_identifier/__init__.py
money_bags/money_identifier/money_identifier.py
money_bags-0.7.0.dist-info/WHEEL
money_bags-0.7.0.dist-info/METADATA
money_bags-0.7.0.dist-info/RECORD
