Metadata-Version: 2.1
Name: money-bags
Version: 0.7.0
Summary: Provides identifying information given various input details.
Author: Your Name
Author-email: you@example.com
Requires-Python: ==3.9.18
Classifier: Programming Language :: Python :: 3
